setup.py
python_gdrive/__init__.py
python_gdrive/client.py
python_gdrive.egg-info/PKG-INFO
python_gdrive.egg-info/SOURCES.txt
python_gdrive.egg-info/dependency_links.txt
python_gdrive.egg-info/requires.txt
python_gdrive.egg-info/top_level.txt