Metadata-Version: 1.1
Name: python-gdrive
Version: 0.3
Summary: Gdrive REST api client
Home-page: https://github.com/cogniteev/python-gdrive
Author: Tony Sanchez
Author-email: tony@cogniteev.com
License: Apache license version 2.0
Download-URL: https://github.com/cogniteev/python-gdrive/archive/master.zip
Platform: OS Independent
Classifier: Programming Language :: Python
Classifier: Programming Language :: Python :: 2.7
Classifier: Intended Audience :: Developers
Classifier: License :: OSI Approved :: Apache Software License
Classifier: Operating System :: OS Independent
Classifier: Topic :: Software Development :: Libraries :: Python Modules
Classifier: Environment :: Web Environment
Classifier: Development Status :: 4 - Beta
